odoo/addons/web_group_expand/README.rst
odoo/addons/web_group_expand/__init__.py
odoo/addons/web_group_expand/__manifest__.py
odoo/addons/web_group_expand/i18n/ca.po
odoo/addons/web_group_expand/i18n/de.po
odoo/addons/web_group_expand/i18n/es.po
odoo/addons/web_group_expand/i18n/fr.po
odoo/addons/web_group_expand/i18n/fr_BE.po
odoo/addons/web_group_expand/i18n/fr_FR.po
odoo/addons/web_group_expand/i18n/it.po
odoo/addons/web_group_expand/i18n/nl.po
odoo/addons/web_group_expand/i18n/pt_BR.po
odoo/addons/web_group_expand/i18n/web_group_expand.pot
odoo/addons/web_group_expand/readme/CONTRIBUTORS.md
odoo/addons/web_group_expand/readme/DESCRIPTION.md
odoo/addons/web_group_expand/static/description/icon.png
odoo/addons/web_group_expand/static/description/index.html
odoo/addons/web_group_expand/static/src/js/list_controller.esm.js
odoo/addons/web_group_expand/static/src/xml/list_controller.xml
odoo_addon_web_group_expand-18.0.1.0.1.5.dist-info/METADATA
odoo_addon_web_group_expand-18.0.1.0.1.5.dist-info/WHEEL
odoo_addon_web_group_expand-18.0.1.0.1.5.dist-info/top_level.txt
odoo_addon_web_group_expand-18.0.1.0.1.5.dist-info/RECORD
