Metadata-Version: 2.1
Name: odoo-addon-web_group_expand
Version: 18.0.1.0.1.5
Requires-Python: >=3.10
Requires-Dist: odoo==18.0.*
Summary: Group Expand Buttons
Home-page: https://github.com/OCA/web
License: AGPL-3
Author: OpenERP SA, AvanzOSC, Serv. Tecnol. Avanzados - Pedro M. Baeza, Therp BV, Xtendoo, Odoo Community Association (OCA)
Author-email: support@odoo-community.org
Classifier: Programming Language :: Python
Classifier: Framework :: Odoo
Classifier: Framework :: Odoo :: 18.0
Classifier: License :: OSI Approved :: GNU Affero General Public License v3
